mlo_optimizer/__init__.py
mlo_optimizer/components/__init__.py
mlo_optimizer/components/algelitism.py
mlo_optimizer/components/genetic_alg.py
mlo_optimizer/config.py
mlo_optimizer/data/__init__.py
mlo_optimizer/data/read.py
mlo_optimizer/descriptors/__init__.py
mlo_optimizer/descriptors/bigram_probs_descriptor.py
mlo_optimizer/descriptors/coef_descriptor.py
mlo_optimizer/descriptors/list_descriptor.py
mlo_optimizer/descriptors/probability_descriptor.py
mlo_optimizer/descriptors/size_descriptor.py
mlo_optimizer/keyboards/__init__.py
mlo_optimizer/keyboards/bigrams.py
mlo_optimizer/keyboards/distances.py
mlo_optimizer/keyboards/fitness.py
mlo_optimizer/optimizer.py
mlo_optimizer-1.0.0.dist-info/LICENSE
mlo_optimizer-1.0.0.dist-info/METADATA
mlo_optimizer-1.0.0.dist-info/WHEEL
mlo_optimizer-1.0.0.dist-info/RECORD
