Metadata-Version: 2.1
Name: mlo-optimizer
Version: 1.0.0
Summary: 
License: Apache-2.0
Keywords: matrix,optimization,genetic,keyboard
Author: Jaskier
Author-email: borody.maxim@gmail.com
Requires-Python: >=3.9,<3.13
Classifier: License :: OSI Approved :: Apache Software License
Classifier: Programming Language :: Python :: 3
Classifier: Programming Language :: Python :: 3.9
Classifier: Programming Language :: Python :: 3.10
Classifier: Programming Language :: Python :: 3.11
Requires-Dist: deap (>=1.3.3,<2.0.0)
Requires-Dist: nltk (>=3.8.1,<4.0.0)
Requires-Dist: numpy (>=1.24.2,<2.0.0)
Requires-Dist: pandas (>=2.0.0,<3.0.0)
Requires-Dist: tqdm (>=4.65.0,<5.0.0)
